Metadata-Version: 2.3
Name: django-q2
Version: 1.7.6
Summary: A multiprocessing distributed task queue for Django
Home-page: https://django-q2.readthedocs.org
License: MIT
Keywords: django,distributed,multiprocessing,queue,scheduler
Author: Stan Triepels
Author-email: django-q2@stantriepels.com
Maintainer: Stan Triepels
Maintainer-email: django-q2@stantriepels.com
Requires-Python: >=3.8,<4
Classifier: Development Status :: 5 - Production/Stable
Classifier: Environment :: Web Environment
Classifier: Framework :: Django
Classifier: Intended Audience :: Developers
Classifier: License :: OSI Approved :: MIT License
Classifier: Operating System :: MacOS
Classifier: Operating System :: POSIX
Classifier: Programming Language :: Python
Classifier: Programming Language :: Python :: 3
Classifier: Programming Language :: Python :: 3.8
Classifier: Programming Language :: Python :: 3.9
Classifier: Programming Language :: Python :: 3.10
Classifier: Programming Language :: Python :: 3.11
Classifier: Programming Language :: Python :: 3.12
Classifier: Programming Language :: Python :: 3.13
Classifier: Topic :: Internet :: WWW/HTTP
Classifier: Topic :: Software Development :: Libraries :: Python Modules
Classifier: Topic :: System :: Distributed Computing
Provides-Extra: build-backend
Provides-Extra: requires
Provides-Extra: rollbar
Provides-Extra: sentry
Provides-Extra: testing
Requires-Dist: blessed (>=1.19.1,<2.0.0) ; extra == "testing"
Requires-Dist: boto3 (>=1.24.92,<2.0.0) ; extra == "testing"
Requires-Dist: croniter (>=2.0.1,<3.0.0) ; extra == "testing"
Requires-Dist: django (>=4.2,<6)
Requires-Dist: django-picklefield (>=3.1,<4.0)
Requires-Dist: django-q-rollbar (>=0.1) ; extra == "rollbar"
Requires-Dist: django-q-sentry (>=0.1) ; extra == "sentry"
Requires-Dist: django-redis (>=5.2.0,<6.0.0) ; extra == "testing"
Requires-Dist: hiredis (>=2.0.0,<3.0.0) ; extra == "testing"
Requires-Dist: importlib-metadata (>=3.6) ; python_version < "3.10"
Requires-Dist: iron-mq (>=0.9,<0.10) ; extra == "testing"
Requires-Dist: psutil (>=5.9.2,<6.0.0) ; extra == "testing"
Requires-Dist: pymongo (>=4.2.0,<5.0.0) ; extra == "testing"
Requires-Dist: redis (>=4.3.4,<5.0.0) ; extra == "testing"
Requires-Dist: setproctitle (>=1.3.2,<2.0.0) ; extra == "testing"
Project-URL: Documentation, https://django-q2.readthedocs.org
Project-URL: Repository, https://github.com/GDay/django-q2
